logitfy/REQUIREMENTS
logitfy/VERSION
logitfy/__init__.py
logitfy/app.py
logitfy/model.py
logitfy/worker.py
logitfy/logitfy-app/dist/index.html
logitfy-1.1.6.dist-info/LICENSE
logitfy-1.1.6.dist-info/METADATA
logitfy-1.1.6.dist-info/WHEEL
logitfy-1.1.6.dist-info/top_level.txt
logitfy-1.1.6.dist-info/RECORD
