Metadata-Version: 2.1
Name: logitfy
Version: 1.1.6
Summary: Create Logging Reports for git Repositories
Home-page: https://github.com/MatthiasRieck/changelog-service
Author: Matthias Rieck
Author-email: Matthias.Rieck@tum.de
License-File: LICENSE
Requires-Dist: fastapi
Requires-Dist: gitaudit >=0.15.9
Requires-Dist: humps
